byoconfig/__init__.py
byoconfig/config.py
byoconfig/config.pyi
byoconfig/error.py
byoconfig/singleton.py
byoconfig/scripts/__init__.py
byoconfig/scripts/build_and_publish.py
byoconfig/scripts/bump_version.py
byoconfig/scripts/common.py
byoconfig/scripts/do_github_release.py
byoconfig/scripts/format_and_lint.py
byoconfig/scripts/run_tests.py
byoconfig/sources/__init__.py
byoconfig/sources/aws_secrets_manager.py
byoconfig/sources/base.py
byoconfig/sources/environment.py
byoconfig/sources/file.py
byoconfig/sources/type_conversion.py
byoconfig-1.1.0.dist-info/licenses/LICENSE
byoconfig-1.1.0.dist-info/METADATA
byoconfig-1.1.0.dist-info/WHEEL
byoconfig-1.1.0.dist-info/entry_points.txt
byoconfig-1.1.0.dist-info/top_level.txt
byoconfig-1.1.0.dist-info/RECORD
