Metadata-Version: 2.4
Name: byoconfig
Version: 1.1.0
Summary: A configuration class that supports plugins, multiple file formats, heirarchical configuration, and more.
Author-email: Cam Ratchford <camratchford@gmail.com>
Project-URL: Homepage, https://github.com/camratchford/byoconfig
Project-URL: Source, https://github.com/camratchford/byoconfig
Keywords: config,yaml,toml,json,plugins
Classifier: Development Status :: 4 - Beta
Classifier: License :: OSI Approved :: MIT License
Classifier: Natural Language :: English
Classifier: Programming Language :: Python
Classifier: Programming Language :: Python :: 3 :: Only
Classifier: Operating System :: Microsoft :: Windows
Classifier: Operating System :: POSIX :: Linux
Classifier: Operating System :: MacOS
Classifier: Environment :: Plugins
Classifier: Intended Audience :: Developers
Classifier: Topic :: Software Development :: Libraries :: Python Modules
Classifier: Topic :: File Formats
Requires-Python: >=3.10
License-File: LICENSE
Requires-Dist: PyYAML
Requires-Dist: toml
Requires-Dist: boto3
Provides-Extra: development
Requires-Dist: setuptools; extra == "development"
Requires-Dist: mkdocs; extra == "development"
Requires-Dist: mkdocs-material; extra == "development"
Requires-Dist: ruff; extra == "development"
Requires-Dist: pytest; extra == "development"
Requires-Dist: build; extra == "development"
Requires-Dist: twine; extra == "development"
Dynamic: license-file
